jinja2xlsx/__init__.py
jinja2xlsx/adjust.py
jinja2xlsx/api.py
jinja2xlsx/config.py
jinja2xlsx/image.py
jinja2xlsx/parse.py
jinja2xlsx/render.py
jinja2xlsx/style.py
jinja2xlsx/testing_utils.py
jinja2xlsx/utils.py
jinja2xlsx-1.2.0.dist-info/WHEEL
jinja2xlsx-1.2.0.dist-info/METADATA
jinja2xlsx-1.2.0.dist-info/RECORD
