Metadata-Version: 2.1
Name: jinja2xlsx
Version: 1.2.0
Summary: Create xlsx-tables from html-tables
Home-page: https://github.com/potykion/jinja2xlsx
License: MIT
Author: potykion
Author-email: potykion@gmail.com
Requires-Python: >=3.7,<4.0
Classifier: License :: OSI Approved :: MIT License
Classifier: Programming Language :: Python :: 3
Classifier: Programming Language :: Python :: 3.7
Classifier: Programming Language :: Python :: 3.8
Classifier: Programming Language :: Python :: 3.9
Provides-Extra: pil
Requires-Dist: cached-property (>=1.5,<2.0)
Requires-Dist: jinja2 (>=3.1,<4.0)
Requires-Dist: openpyxl (>=3.0,<4.0)
Requires-Dist: pillow (>=9.4,<10.0); extra == "pil"
Requires-Dist: requests-html (>=0.10.0,<0.11.0)
Project-URL: Repository, https://github.com/potykion/jinja2xlsx
